{
  "project_info": {
    "project_number": "616591151137",
    "project_id": "chatapp-cb42a",
    "storage_bucket": "chatapp-cb42a.appspot.com"
  },
  "client": [
    {
      "client_info": {
        "mobilesdk_app_id": "1:616591151137:android:b5d859259eebbb9c135360",
        "android_client_info": {
          "package_name": "com.example.chatapp_project"
        }
      },
      "oauth_client": [],
      "api_key": [
        {
          "current_key": "AIzaSyDU3gZ_uy46DhKSdGB2RZ0NqBOSCSuOSnQ"
        }
      ],
      "services": {
        "appinvite_service": {
          "other_platform_oauth_client": []
        }
      }
    }
  ],
  "configuration_version": "1"
}